doger/__init__.py
doger/__version__.py
doger/formatter.py
doger/handlers.py
doger/output.py
doger/pythonjsonlogger/__init__.py
doger/pythonjsonlogger/jsonlogger.py
doger/tests/__init__.py
doger/tests/test_daiquiri.py
doger/tests/test_formatter.py
doger/tests/test_output.py
doger-0.0.4.dist-info/LICENSE
doger-0.0.4.dist-info/METADATA
doger-0.0.4.dist-info/WHEEL
doger-0.0.4.dist-info/top_level.txt
doger-0.0.4.dist-info/RECORD
