Metadata-Version: 2.1
Name: doger
Version: 0.0.4
Summary: An awesome log utils for python, enjoy~
Home-page: https://github.com/szj2ys/doger
Author: szj
Author-email: szj2ys@qq.com
License: MIT
Platform: UNKNOWN
Classifier: License :: OSI Approved :: MIT License
Classifier: Programming Language :: Python :: 3.7
Classifier: Programming Language :: Python :: 3.8
Classifier: Programming Language :: Python :: Implementation :: PyPy
Requires-Python: >=3.6.0
Requires-Dist: just
Requires-Dist: loguru
Requires-Dist: environs
Requires-Dist: joblib
Requires-Dist: psutil
Requires-Dist: twine
Requires-Dist: fastcache
Requires-Dist: glob2
